zoundcard/__init__.py
zoundcard/core.py
zoundcard-0.1.0.dist-info/METADATA
zoundcard-0.1.0.dist-info/WHEEL
zoundcard-0.1.0.dist-info/entry_points.txt
zoundcard-0.1.0.dist-info/licenses/LICENSE
zoundcard-0.1.0.dist-info/RECORD
