Metadata-Version: 2.3
Name: zoundcard
Version: 0.1.0
Summary: Using the pyaudio and zignal libraries to play audio on a soundcard
Project-URL: Homepage, https://github.com/ronnyandersson/zoundcard
Project-URL: Issues, https://github.com/ronnyandersson/zoundcard/issues
Project-URL: Download, https://pypi.python.org/pypi/zoundcard
Author-email: Ronny Andersson <ronny@andersson.tk>
License: MIT License
License-File: LICENSE
Keywords: audio,card,playback,portaudio,pyaudio,recording,sound,soundcard
Classifier: Development Status :: 3 - Alpha
Classifier: Environment :: Console
Classifier: Intended Audience :: Developers
Classifier: Intended Audience :: Education
Classifier: Intended Audience :: Science/Research
Classifier: License :: OSI Approved :: MIT License
Classifier: Operating System :: OS Independent
Classifier: Programming Language :: Python :: 3
Classifier: Topic :: Multimedia :: Sound/Audio :: Capture/Recording
Classifier: Topic :: Multimedia :: Sound/Audio :: Players
Classifier: Topic :: Software Development :: Quality Assurance
Classifier: Topic :: Software Development :: Testing
Requires-Python: >=3.8
Requires-Dist: numpy
Requires-Dist: pyaudio
Requires-Dist: zignal
Provides-Extra: dev
Requires-Dist: flake8; extra == 'dev'
Requires-Dist: isort; extra == 'dev'
